MANIFEST.in
README.md
_festival.cpp
festival.py
festival_private.h
setup.py
pyfestival.egg-info/PKG-INFO
pyfestival.egg-info/SOURCES.txt
pyfestival.egg-info/dependency_links.txt
pyfestival.egg-info/top_level.txt