Metadata-Version: 1.0
Name: pyfestival
Version: 0.6
Summary: Python Festival module
Home-page: https://github.com/techiaith/pyfestival
Author: Patrick Robertson
Author-email: techiaith@bangor.ac.uk
License: BSD
Platform: *nix
